MANIFEST.in
README.txt
setup.cfg
setup.py
docs/HISTORY.txt
pyjon/__init__.py
pyjon.events.egg-info/PKG-INFO
pyjon.events.egg-info/SOURCES.txt
pyjon.events.egg-info/dependency_links.txt
pyjon.events.egg-info/entry_points.txt
pyjon.events.egg-info/namespace_packages.txt
pyjon.events.egg-info/not-zip-safe
pyjon.events.egg-info/requires.txt
pyjon.events.egg-info/top_level.txt
pyjon/events/__init__.py
pyjon/events/dispatcher.py