Metadata-Version: 1.0
Name: pyjon.events
Version: 1.1.1
Summary: Pyjon.Events is an easy-to-use event dispatcher
Home-page: UNKNOWN
Author: Jonathan Schemoul
Author-email: jonathan.schemoul@gmail.com
License: MIT
Keywords: pyjon events hub factory metaclass
Platform: UNKNOWN
Classifier: Programming Language :: Python
Classifier: Topic :: Software Development :: Libraries :: Python Modules
